{
  "story_id": "501021800",
  "casts": [
    0,
    1034,
    1006,
    1071,
    1072,
    90001,
    1021,
    -1
  ],
  "frames": {
    "0": {
      "frame_id": 0,
      "background_id": 150,
      "sub_background_id": 130,
      "cg": "",
      "animated_cg": null,
      "dialogue": [
        {
          "next_frame": 1,
          "character_id": -1,
          "speaker_name": "",
          "text": "",
          "flag_type": "",
          "flag": "",
          "choices": []
        }
      ]
    },
    "1": {
      "frame_id": 1,
      "background_id": 150,
      "sub_background_id": 130,
      "cg": "",
      "animated_cg": null,
      "dialogue": [
        {
          "next_frame": 2,
          "character_id": 1021,
          "speaker_name": "タマモクロス",
          "text": "ほな、みんな！　曳神輿、 気合い入れて引っ張りぃやー！",
          "flag_type": "",
          "flag": "",
          "choices": []
        }
      ]
    },
    "2": {
      "frame_id": 2,
      "background_id": 150,
      "sub_background_id": 130,
      "cg": "",
      "animated_cg": null,
      "dialogue": [
        {
          "next_frame": 3,
          "character_id": 1034,
          "speaker_name": "イナリワン",
          "text": "せーのっ、せーい！！",
          "flag_type": "",
          "flag": "",
          "choices": []
        }
      ]
    },
    "3": {
      "frame_id": 3,
      "background_id": 37,
      "sub_background_id": 130,
      "cg": "",
      "animated_cg": null,
      "dialogue": [
        {
          "next_frame": 4,
          "character_id": 0,
          "speaker_name": "ウマ娘たち",
          "text": "むごごごごご……！",
          "flag_type": "",
          "flag": "",
          "choices": []
        }
      ]
    },
    "4": {
      "frame_id": 4,
      "background_id": 150,
      "sub_background_id": 130,
      "cg": "",
      "animated_cg": null,
      "dialogue": [
        {
          "next_frame": 5,
          "character_id": 1034,
          "speaker_name": "イナリワン",
          "text": "おいおい、梃子でも動かねえじゃねえか。 参ったな、こりゃ……。",
          "flag_type": "",
          "flag": "",
          "choices": []
        }
      ]
    },
    "5": {
      "frame_id": 5,
      "background_id": 150,
      "sub_background_id": 130,
      "cg": "",
      "animated_cg": null,
      "dialogue": [
        {
          "next_frame": 6,
          "character_id": 90001,
          "speaker_name": "モノローグ",
          "text": "秋の祭礼『駿大祭』当日。 『曳神輿』を先導するタマモクロスと イナリワンだったが……。",
          "flag_type": "",
          "flag": "",
          "choices": []
        }
      ]
    },
    "6": {
      "frame_id": 6,
      "background_id": 150,
      "sub_background_id": 130,
      "cg": "",
      "animated_cg": null,
      "dialogue": [
        {
          "next_frame": 7,
          "character_id": 1071,
          "speaker_name": "メジロアルダン",
          "text": "思ったより重いですね……。 重戦車級――というのでしょうか。",
          "flag_type": "",
          "flag": "",
          "choices": []
        }
      ]
    },
    "7": {
      "frame_id": 7,
      "background_id": 150,
      "sub_background_id": 130,
      "cg": "",
      "animated_cg": null,
      "dialogue": [
        {
          "next_frame": 8,
          "character_id": 1034,
          "speaker_name": "イナリワン",
          "text": "アルダン、そう、しょげるなってんでい。 要は足りないのは……。",
          "flag_type": "",
          "flag": "",
          "choices": []
        }
      ]
    },
    "8": {
      "frame_id": 8,
      "background_id": 150,
      "sub_background_id": 130,
      "cg": "",
      "animated_cg": null,
      "dialogue": [
        {
          "next_frame": 9,
          "character_id": 1034,
          "speaker_name": "イナリワン",
          "text": "気合いでーい！！！",
          "flag_type": "",
          "flag": "",
          "choices": []
        }
      ]
    },
    "9": {
      "frame_id": 9,
      "background_id": 150,
      "sub_background_id": 130,
      "cg": "",
      "animated_cg": null,
      "dialogue": [
        {
          "next_frame": 10,
          "character_id": 1021,
          "speaker_name": "タマモクロス",
          "text": "まあ待ちや、イナリ。こんだけバラバラじゃ、 気合いだけじゃ、どうにもならんやろ。",
          "flag_type": "",
          "flag": "",
          "choices": []
        }
      ]
    },
    "10": {
      "frame_id": 10,
      "background_id": 150,
      "sub_background_id": 130,
      "cg": "",
      "animated_cg": null,
      "dialogue": [
        {
          "next_frame": 11,
          "character_id": 1021,
          "speaker_name": "タマモクロス",
          "text": "息が合わん理由はそれぞれなんや。 だから……。",
          "flag_type": "",
          "flag": "",
          "choices": []
        }
      ]
    },
    "11": {
      "frame_id": 11,
      "background_id": 150,
      "sub_background_id": 130,
      "cg": "",
      "animated_cg": null,
      "dialogue": [
        {
          "next_frame": 12,
          "character_id": 1021,
          "speaker_name": "タマモクロス",
          "text": "ひとりひとりと、よう話さんとな。 チビたちに言い聞かせるように。",
          "flag_type": "",
          "flag": "",
          "choices": []
        }
      ]
    },
    "12": {
      "frame_id": 12,
      "background_id": 150,
      "sub_background_id": 130,
      "cg": "",
      "animated_cg": null,
      "dialogue": [
        {
          "next_frame": 13,
          "character_id": 1021,
          "speaker_name": "タマモクロス",
          "text": "アルダン、どないしたん？ 何迷ってんねん？",
          "flag_type": "",
          "flag": "",
          "choices": []
        }
      ]
    },
    "13": {
      "frame_id": 13,
      "background_id": 150,
      "sub_background_id": 130,
      "cg": "",
      "animated_cg": null,
      "dialogue": [
        {
          "next_frame": 14,
          "character_id": 1071,
          "speaker_name": "メジロアルダン",
          "text": "いえ、その……周りと呼吸を 合わせなければと、つい様子を見てしまって。",
          "flag_type": "",
          "flag": "",
          "choices": []
        }
      ]
    },
    "14": {
      "frame_id": 14,
      "background_id": 150,
      "sub_background_id": 130,
      "cg": "",
      "animated_cg": null,
      "dialogue": [
        {
          "next_frame": 15,
          "character_id": 1021,
          "speaker_name": "タマモクロス",
          "text": "考えすぎや。そんなんしてたら、 どうしても一呼吸、遅れるやろ。",
          "flag_type": "",
          "flag": "",
          "choices": []
        }
      ]
    },
    "15": {
      "frame_id": 15,
      "background_id": 150,
      "sub_background_id": 130,
      "cg": "",
      "animated_cg": null,
      "dialogue": [
        {
          "next_frame": 16,
          "character_id": 1021,
          "speaker_name": "タマモクロス",
          "text": "やりたいようにやってみ！ 大丈夫、周りを信じろや。",
          "flag_type": "",
          "flag": "",
          "choices": []
        }
      ]
    },
    "16": {
      "frame_id": 16,
      "background_id": 150,
      "sub_background_id": 130,
      "cg": "",
      "animated_cg": null,
      "dialogue": [
        {
          "next_frame": 17,
          "character_id": 1072,
          "speaker_name": "ヤエノムテキ",
          "text": "タマモさん。私は逆に、 どうしても先走ってしまって……。",
          "flag_type": "",
          "flag": "",
          "choices": []
        }
      ]
    },
    "17": {
      "frame_id": 17,
      "background_id": 150,
      "sub_background_id": 130,
      "cg": "",
      "animated_cg": null,
      "dialogue": [
        {
          "next_frame": 18,
          "character_id": 1021,
          "speaker_name": "タマモクロス",
          "text": "あー、ヤエノは武術やってるやろ？ だから集中しすぎなんや。",
          "flag_type": "",
          "flag": "",
          "choices": []
        }
      ]
    },
    "18": {
      "frame_id": 18,
      "background_id": 150,
      "sub_background_id": 130,
      "cg": "",
      "animated_cg": null,
      "dialogue": [
        {
          "next_frame": 19,
          "character_id": 1021,
          "speaker_name": "タマモクロス",
          "text": "そんな稲妻みたいに動き出さんでええねん。 一拍置いて、ノンビリやりーや。",
          "flag_type": "",
          "flag": "",
          "choices": []
        }
      ]
    },
    "19": {
      "frame_id": 19,
      "background_id": 150,
      "sub_background_id": 130,
      "cg": "",
      "animated_cg": null,
      "dialogue": [
        {
          "next_frame": 20,
          "character_id": 1006,
          "speaker_name": "オグリキャップ",
          "text": "タマ、私は……。",
          "flag_type": "",
          "flag": "",
          "choices": []
        }
      ]
    },
    "20": {
      "frame_id": 20,
      "background_id": 150,
      "sub_background_id": 130,
      "cg": "",
      "animated_cg": null,
      "dialogue": [
        {
          "next_frame": 21,
          "character_id": 1021,
          "speaker_name": "タマモクロス",
          "text": "オマエは――",
          "flag_type": "",
          "flag": "",
          "choices": []
        }
      ]
    },
    "21": {
      "frame_id": 21,
      "background_id": 150,
      "sub_background_id": 130,
      "cg": "",
      "animated_cg": null,
      "dialogue": [
        {
          "next_frame": 22,
          "character_id": 1021,
          "speaker_name": "タマモクロス",
          "text": "終わったら、飯食わせたる！",
          "flag_type": "",
          "flag": "",
          "choices": []
        }
      ]
    },
    "22": {
      "frame_id": 22,
      "background_id": 150,
      "sub_background_id": 130,
      "cg": "",
      "animated_cg": null,
      "dialogue": [
        {
          "next_frame": 23,
          "character_id": 1006,
          "speaker_name": "オグリキャップ",
          "text": "わかった！　うん、頑張るぞ！",
          "flag_type": "",
          "flag": "",
          "choices": []
        }
      ]
    },
    "23": {
      "frame_id": 23,
      "background_id": 150,
      "sub_background_id": 130,
      "cg": "",
      "animated_cg": null,
      "dialogue": [
        {
          "next_frame": 24,
          "character_id": 1034,
          "speaker_name": "イナリワン",
          "text": "よーし！　今度こそ、バッチシ キメるぜい！",
          "flag_type": "",
          "flag": "",
          "choices": []
        }
      ]
    },
    "24": {
      "frame_id": 24,
      "background_id": 150,
      "sub_background_id": 130,
      "cg": "",
      "animated_cg": null,
      "dialogue": [
        {
          "next_frame": 25,
          "character_id": 1034,
          "speaker_name": "イナリワン",
          "text": "せーのっ、せーい！！",
          "flag_type": "",
          "flag": "",
          "choices": []
        }
      ]
    },
    "25": {
      "frame_id": 25,
      "background_id": 37,
      "sub_background_id": 130,
      "cg": "",
      "animated_cg": null,
      "dialogue": [
        {
          "next_frame": 26,
          "character_id": 0,
          "speaker_name": "ウマ娘たち",
          "text": "うおおおおおお……！",
          "flag_type": "",
          "flag": "",
          "choices": []
        }
      ]
    },
    "26": {
      "frame_id": 26,
      "background_id": 150,
      "sub_background_id": 130,
      "cg": "",
      "animated_cg": null,
      "dialogue": [
        {
          "next_frame": 27,
          "character_id": 1034,
          "speaker_name": "イナリワン",
          "text": "おおお、やったぞ、タマ！ これこそ火事場のバカヂカラでい！",
          "flag_type": "",
          "flag": "",
          "choices": []
        }
      ]
    },
    "27": {
      "frame_id": 27,
      "background_id": 150,
      "sub_background_id": 130,
      "cg": "",
      "animated_cg": null,
      "dialogue": [
        {
          "next_frame": 28,
          "character_id": 1021,
          "speaker_name": "タマモクロス",
          "text": "へへっ、な、言うたやろ？ まずは手を貸してやることや。",
          "flag_type": "",
          "flag": "",
          "choices": []
        }
      ]
    },
    "28": {
      "frame_id": 28,
      "background_id": 150,
      "sub_background_id": 130,
      "cg": "",
      "animated_cg": null,
      "dialogue": [
        {
          "next_frame": 29,
          "character_id": 90001,
          "speaker_name": "モノローグ",
          "text": "タマモクロスの細やかなリーダーシップに より、神輿は自由に練り歩けるようになった。",
          "flag_type": "",
          "flag": "",
          "choices": []
        }
      ]
    },
    "29": {
      "frame_id": 29,
      "background_id": 150,
      "sub_background_id": 130,
      "cg": "",
      "animated_cg": null,
      "dialogue": [
        {
          "next_frame": 30,
          "character_id": 1021,
          "speaker_name": "タマモクロス",
          "text": "でトレーナー。 この神輿、どんなふうに引っ張りまわそか。 楽しく遊ぶか、荒々しくやるか！",
          "flag_type": "",
          "flag": "",
          "choices": []
        }
      ]
    },
    "30": {
      "frame_id": 30,
      "background_id": 150,
      "sub_background_id": 130,
      "cg": "",
      "animated_cg": null,
      "dialogue": [
        {
          "next_frame": 31,
          "character_id": 90001,
          "speaker_name": "モノローグ",
          "text": "せっかくのお祭り。 1番盛り上げるためには――",
          "flag_type": "",
          "flag": "",
          "choices": [
            {
              "next_frame": 31,
              "loop_ends_at_frame": -1,
              "text": "子どもと一緒に楽しく",
              "flag_type": "",
              "flag": ""
            },
            {
              "next_frame": 43,
              "loop_ends_at_frame": -1,
              "text": "ド派手に神輿バトル！",
              "flag_type": "",
              "flag": ""
            }
          ]
        }
      ]
    },
    "31": {
      "frame_id": 31,
      "background_id": 150,
      "sub_background_id": 130,
      "cg": "",
      "animated_cg": null,
      "dialogue": [
        {
          "next_frame": 32,
          "character_id": 1021,
          "speaker_name": "タマモクロス",
          "text": "子どもと一緒にか！　せやな、 せっかくならチビらもまぜたろ。",
          "flag_type": "",
          "flag": "",
          "choices": []
        }
      ]
    },
    "32": {
      "frame_id": 32,
      "background_id": 150,
      "sub_background_id": 130,
      "cg": "",
      "animated_cg": null,
      "dialogue": [
        {
          "next_frame": 33,
          "character_id": 1021,
          "speaker_name": "タマモクロス",
          "text": "みんなー！　こっち来いやー！　ウチらが 神輿の引っ張り方、教えたるでー！",
          "flag_type": "",
          "flag": "",
          "choices": []
        }
      ]
    },
    "33": {
      "frame_id": 33,
      "background_id": 150,
      "sub_background_id": 130,
      "cg": "",
      "animated_cg": null,
      "dialogue": [
        {
          "next_frame": 34,
          "character_id": 1006,
          "speaker_name": "オグリキャップ",
          "text": "うん、いいぞ。もっとお腹に力を入れて……。",
          "flag_type": "",
          "flag": "",
          "choices": []
        }
      ]
    },
    "34": {
      "frame_id": 34,
      "background_id": 150,
      "sub_background_id": 130,
      "cg": "",
      "animated_cg": null,
      "dialogue": [
        {
          "next_frame": 35,
          "character_id": 1072,
          "speaker_name": "ヤエノムテキ",
          "text": "呼吸が大切です。神輿と体をひとつに 重ね合わせるイメージで……。",
          "flag_type": "",
          "flag": "",
          "choices": []
        }
      ]
    },
    "35": {
      "frame_id": 35,
      "background_id": 150,
      "sub_background_id": 130,
      "cg": "",
      "animated_cg": null,
      "dialogue": [
        {
          "next_frame": 36,
          "character_id": 1071,
          "speaker_name": "メジロアルダン",
          "text": "ひ、引っ張るのは私の髪ではありませんよ？ ちゃんとお神輿に集中して、ね。",
          "flag_type": "",
          "flag": "",
          "choices": []
        }
      ]
    },
    "36": {
      "frame_id": 36,
      "background_id": 150,
      "sub_background_id": 130,
      "cg": "",
      "animated_cg": null,
      "dialogue": [
        {
          "next_frame": 37,
          "character_id": 1034,
          "speaker_name": "イナリワン",
          "text": "へえ、お前んち、あの鎮守様の裏なのか。 やるじゃねえか！",
          "flag_type": "",
          "flag": "",
          "choices": []
        }
      ]
    },
    "37": {
      "frame_id": 37,
      "background_id": 150,
      "sub_background_id": 130,
      "cg": "",
      "animated_cg": null,
      "dialogue": [
        {
          "next_frame": 38,
          "character_id": 1021,
          "speaker_name": "タマモクロス",
          "text": "へへっ、トレーナー。やっぱ、こんなふうに みんなで盛り上がるのが1番やな。",
          "flag_type": "",
          "flag": "",
          "choices": []
        }
      ]
    },
    "38": {
      "frame_id": 38,
      "background_id": 150,
      "sub_background_id": 130,
      "cg": "",
      "animated_cg": null,
      "dialogue": [
        {
          "next_frame": 39,
          "character_id": 1021,
          "speaker_name": "タマモクロス",
          "text": "大阪のチビたちにも、写真送ったろ。",
          "flag_type": "",
          "flag": "",
          "choices": []
        }
      ]
    },
    "39": {
      "frame_id": 39,
      "background_id": 150,
      "sub_background_id": 130,
      "cg": "",
      "animated_cg": null,
      "dialogue": [
        {
          "next_frame": 40,
          "character_id": 1021,
          "speaker_name": "タマモクロス",
          "text": "おいイナリ。 みんなを連れて、こっち来いや！",
          "flag_type": "",
          "flag": "",
          "choices": []
        }
      ]
    },
    "40": {
      "frame_id": 40,
      "background_id": 150,
      "sub_background_id": 130,
      "cg": "",
      "animated_cg": null,
      "dialogue": [
        {
          "next_frame": 41,
          "character_id": 1034,
          "speaker_name": "イナリワン",
          "text": "おう！",
          "flag_type": "",
          "flag": "",
          "choices": []
        }
      ]
    },
    "41": {
      "frame_id": 41,
      "background_id": 150,
      "sub_background_id": 130,
      "cg": "",
      "animated_cg": null,
      "dialogue": [
        {
          "next_frame": 42,
          "character_id": 90001,
          "speaker_name": "モノローグ",
          "text": "（カシャ！）",
          "flag_type": "",
          "flag": "",
          "choices": []
        }
      ]
    },
    "42": {
      "frame_id": 42,
      "background_id": 150,
      "sub_background_id": 130,
      "cg": "",
      "animated_cg": null,
      "dialogue": [
        {
          "next_frame": -1,
          "character_id": 90001,
          "speaker_name": "モノローグ",
          "text": "子どもたちとほのぼの交流。 大騒ぎするだけが祭りじゃないと学んだ タマモクロスだった。",
          "flag_type": "",
          "flag": "",
          "choices": []
        }
      ]
    },
    "43": {
      "frame_id": 43,
      "background_id": 150,
      "sub_background_id": 130,
      "cg": "",
      "animated_cg": null,
      "dialogue": [
        {
          "next_frame": 44,
          "character_id": 1021,
          "speaker_name": "タマモクロス",
          "text": "おおお、神輿バトル！ 熱いやんか、トレーナー！",
          "flag_type": "",
          "flag": "",
          "choices": []
        }
      ]
    },
    "44": {
      "frame_id": 44,
      "background_id": 150,
      "sub_background_id": 130,
      "cg": "",
      "animated_cg": null,
      "dialogue": [
        {
          "next_frame": 45,
          "character_id": 1021,
          "speaker_name": "タマモクロス",
          "text": "それじゃオマエら、どの神輿が1番速くて 強いか、勝負しにいくでー！",
          "flag_type": "",
          "flag": "",
          "choices": []
        }
      ]
    },
    "45": {
      "frame_id": 45,
      "background_id": 150,
      "sub_background_id": 130,
      "cg": "",
      "animated_cg": null,
      "dialogue": [
        {
          "next_frame": 46,
          "character_id": 1034,
          "speaker_name": "イナリワン",
          "text": "おう！　やってやろーじゃねえか！",
          "flag_type": "",
          "flag": "",
          "choices": []
        }
      ]
    },
    "46": {
      "frame_id": 46,
      "background_id": 150,
      "sub_background_id": 130,
      "cg": "",
      "animated_cg": null,
      "dialogue": [
        {
          "next_frame": 47,
          "character_id": 1034,
          "speaker_name": "イナリワン",
          "text": "でもタマ、さっきの優しい教えっぷりとは えらい違いだな。",
          "flag_type": "",
          "flag": "",
          "choices": []
        }
      ]
    },
    "47": {
      "frame_id": 47,
      "background_id": 150,
      "sub_background_id": 130,
      "cg": "",
      "animated_cg": null,
      "dialogue": [
        {
          "next_frame": 48,
          "character_id": 1021,
          "speaker_name": "タマモクロス",
          "text": "当ったり前や。ていねいに教えたんは 団結して、勝負所で一緒に勝つためやろ。",
          "flag_type": "",
          "flag": "",
          "choices": []
        }
      ]
    },
    "48": {
      "frame_id": 48,
      "background_id": 150,
      "sub_background_id": 130,
      "cg": "",
      "animated_cg": null,
      "dialogue": [
        {
          "next_frame": 49,
          "character_id": 1021,
          "speaker_name": "タマモクロス",
          "text": "さあ、浪速のド根性見せたるでー！ だんじりじゃーーーい！！",
          "flag_type": "",
          "flag": "",
          "choices": []
        }
      ]
    },
    "49": {
      "frame_id": 49,
      "background_id": 37,
      "sub_background_id": 630,
      "cg": "",
      "animated_cg": null,
      "dialogue": [
        {
          "next_frame": -1,
          "character_id": 90001,
          "speaker_name": "モノローグ",
          "text": "だんじり……ではない。がタマモクロスは 秋の祭礼で思いっきり派手に暴れまわった。",
          "flag_type": "",
          "flag": "",
          "choices": []
        }
      ]
    }
  }
}