{
  "story_id": "830075003",
  "casts": [
    1025,
    90001,
    -1,
    0
  ],
  "frames": {
    "0": {
      "frame_id": 0,
      "background_id": 74,
      "sub_background_id": 130,
      "cg": "",
      "animated_cg": null,
      "dialogue": [
        {
          "next_frame": 1,
          "character_id": -1,
          "speaker_name": "",
          "text": "",
          "flag_type": "",
          "flag": "",
          "choices": []
        }
      ]
    },
    "1": {
      "frame_id": 1,
      "background_id": 74,
      "sub_background_id": 130,
      "cg": "",
      "animated_cg": null,
      "dialogue": [
        {
          "next_frame": 2,
          "character_id": 90001,
          "speaker_name": "モノローグ",
          "text": "夜のトレーニングコースは静かだ。\r 考え事をするにはちょうどいい。",
          "flag_type": "",
          "flag": "",
          "choices": []
        }
      ]
    },
    "2": {
      "frame_id": 2,
      "background_id": 74,
      "sub_background_id": 130,
      "cg": "",
      "animated_cg": null,
      "dialogue": [
        {
          "next_frame": 3,
          "character_id": 90001,
          "speaker_name": "モノローグ",
          "text": "そう思い、観客席で\r 明日のトレーニングメニューを 考えていると――",
          "flag_type": "",
          "flag": "",
          "choices": []
        }
      ]
    },
    "3": {
      "frame_id": 3,
      "background_id": 74,
      "sub_background_id": 130,
      "cg": "",
      "animated_cg": null,
      "dialogue": [
        {
          "next_frame": 4,
          "character_id": 1025,
          "speaker_name": "マンハッタンカフェ",
          "text": "……こんばんは……。\r こんな時間まで……お仕事ですか……？",
          "flag_type": "",
          "flag": "",
          "choices": []
        }
      ]
    },
    "4": {
      "frame_id": 4,
      "background_id": 74,
      "sub_background_id": 130,
      "cg": "",
      "animated_cg": null,
      "dialogue": [
        {
          "next_frame": 5,
          "character_id": 1025,
          "speaker_name": "マンハッタンカフェ",
          "text": "トレーナーのお仕事って……\r ……大変……ですね……。",
          "flag_type": "",
          "flag": "",
          "choices": [
            {
              "next_frame": 5,
              "loop_ends_at_frame": -1,
              "text": "このくらいどうってこと――",
              "flag_type": "",
              "flag": ""
            }
          ]
        }
      ]
    },
    "5": {
      "frame_id": 5,
      "background_id": 74,
      "sub_background_id": 130,
      "cg": "",
      "animated_cg": null,
      "dialogue": [
        {
          "next_frame": 6,
          "character_id": 90001,
          "speaker_name": "モノローグ",
          "text": "マンハッタンカフェと話していると、\r ふいに走る音が聞こえた。 辺りを見回すと、そこには――",
          "flag_type": "",
          "flag": "",
          "choices": []
        }
      ]
    },
    "6": {
      "frame_id": 6,
      "background_id": 9,
      "sub_background_id": 140,
      "cg": "",
      "animated_cg": null,
      "dialogue": [
        {
          "next_frame": 7,
          "character_id": 0,
          "speaker_name": "明るい髪色のウマ娘",
          "text": "はっ、はぁ……ハァアァァア！",
          "flag_type": "",
          "flag": "",
          "choices": []
        }
      ]
    },
    "7": {
      "frame_id": 7,
      "background_id": 74,
      "sub_background_id": 130,
      "cg": "",
      "animated_cg": null,
      "dialogue": [
        {
          "next_frame": 8,
          "character_id": 1025,
          "speaker_name": "マンハッタンカフェ",
          "text": "彼女……は……。",
          "flag_type": "",
          "flag": "",
          "choices": []
        }
      ]
    },
    "8": {
      "frame_id": 8,
      "background_id": 70,
      "sub_background_id": 110,
      "cg": "",
      "animated_cg": null,
      "dialogue": [
        {
          "next_frame": 9,
          "character_id": 0,
          "speaker_name": "明るい髪色のウマ娘",
          "text": "1人黙々とトレーニングを続ける\r カフェさんのこと、 すごいなぁって思ってたんです！",
          "flag_type": "",
          "flag": "",
          "choices": []
        }
      ]
    },
    "9": {
      "frame_id": 9,
      "background_id": 74,
      "sub_background_id": 130,
      "cg": "",
      "animated_cg": null,
      "dialogue": [
        {
          "next_frame": 10,
          "character_id": 1025,
          "speaker_name": "マンハッタンカフェ",
          "text": "……彼女の走り……\r あれは……。",
          "flag_type": "",
          "flag": "",
          "choices": []
        }
      ]
    },
    "10": {
      "frame_id": 10,
      "background_id": 37,
      "sub_background_id": 130,
      "cg": "",
      "animated_cg": null,
      "dialogue": [
        {
          "next_frame": 11,
          "character_id": 0,
          "speaker_name": "明るい髪色のウマ娘",
          "text": "もっと……もっと、速く……！\r あの背中を……見失ったりしない……！",
          "flag_type": "",
          "flag": "",
          "choices": []
        }
      ]
    },
    "11": {
      "frame_id": 11,
      "background_id": 37,
      "sub_background_id": 130,
      "cg": "",
      "animated_cg": null,
      "dialogue": [
        {
          "next_frame": 12,
          "character_id": 90001,
          "speaker_name": "モノローグ",
          "text": "切実で必死な目。\r 見えない『誰か』を追うような その走りは、まるで――",
          "flag_type": "",
          "flag": "",
          "choices": [
            {
              "next_frame": 12,
              "loop_ends_at_frame": -1,
              "text": "マンハッタンカフェみたいだ",
              "flag_type": "",
              "flag": "male_trainer"
            },
            {
              "next_frame": 12,
              "loop_ends_at_frame": -1,
              "text": "マンハッタンカフェみたいだね",
              "flag_type": "",
              "flag": "female_trainer"
            }
          ]
        }
      ]
    },
    "12": {
      "frame_id": 12,
      "background_id": 37,
      "sub_background_id": 130,
      "cg": "",
      "animated_cg": null,
      "dialogue": [
        {
          "next_frame": 13,
          "character_id": 1025,
          "speaker_name": "マンハッタンカフェ",
          "text": "え……？",
          "flag_type": "",
          "flag": "",
          "choices": []
        }
      ]
    },
    "13": {
      "frame_id": 13,
      "background_id": 74,
      "sub_background_id": 130,
      "cg": "",
      "animated_cg": null,
      "dialogue": [
        {
          "next_frame": 14,
          "character_id": 1025,
          "speaker_name": "マンハッタンカフェ",
          "text": "……私……ですか……？",
          "flag_type": "",
          "flag": "",
          "choices": []
        }
      ]
    },
    "14": {
      "frame_id": 14,
      "background_id": 74,
      "sub_background_id": 130,
      "cg": "",
      "animated_cg": null,
      "dialogue": [
        {
          "next_frame": 15,
          "character_id": 1025,
          "speaker_name": "マンハッタンカフェ",
          "text": "…………。彼女も……また何かを……\r 追いかけている……？",
          "flag_type": "",
          "flag": "",
          "choices": []
        }
      ]
    },
    "15": {
      "frame_id": 15,
      "background_id": 74,
      "sub_background_id": 130,
      "cg": "",
      "animated_cg": null,
      "dialogue": [
        {
          "next_frame": 16,
          "character_id": 1025,
          "speaker_name": "マンハッタンカフェ",
          "text": "でも……彼女の前には……何も……。",
          "flag_type": "",
          "flag": "",
          "choices": []
        }
      ]
    },
    "16": {
      "frame_id": 16,
      "background_id": 9,
      "sub_background_id": 140,
      "cg": "",
      "animated_cg": null,
      "dialogue": [
        {
          "next_frame": 17,
          "character_id": 0,
          "speaker_name": "明るい髪色のウマ娘",
          "text": "ふー……よし、もう1度っ。\r 大丈夫、大丈夫！　いける、いける！ 疲れてないし、まだまだ――",
          "flag_type": "",
          "flag": "",
          "choices": []
        }
      ]
    },
    "17": {
      "frame_id": 17,
      "background_id": 9,
      "sub_background_id": 140,
      "cg": "",
      "animated_cg": null,
      "dialogue": [
        {
          "next_frame": 18,
          "character_id": 0,
          "speaker_name": "明るい髪色のウマ娘",
          "text": "……？　あ……カフェさん！？",
          "flag_type": "",
          "flag": "",
          "choices": []
        }
      ]
    },
    "18": {
      "frame_id": 18,
      "background_id": 74,
      "sub_background_id": 130,
      "cg": "",
      "animated_cg": null,
      "dialogue": [
        {
          "next_frame": 19,
          "character_id": 0,
          "speaker_name": "明るい髪色のウマ娘",
          "text": "こんばんは！　あのっ、よかったら\r 今日も一緒に――",
          "flag_type": "",
          "flag": "",
          "choices": []
        }
      ]
    },
    "19": {
      "frame_id": 19,
      "background_id": 74,
      "sub_background_id": 130,
      "cg": "",
      "animated_cg": null,
      "dialogue": [
        {
          "next_frame": 20,
          "character_id": 1025,
          "speaker_name": "マンハッタンカフェ",
          "text": "……アナタは……。",
          "flag_type": "",
          "flag": "",
          "choices": []
        }
      ]
    },
    "20": {
      "frame_id": 20,
      "background_id": 74,
      "sub_background_id": 130,
      "cg": "",
      "animated_cg": null,
      "dialogue": [
        {
          "next_frame": 21,
          "character_id": 0,
          "speaker_name": "明るい髪色のウマ娘",
          "text": "？　はい？",
          "flag_type": "",
          "flag": "",
          "choices": []
        }
      ]
    },
    "21": {
      "frame_id": 21,
      "background_id": 74,
      "sub_background_id": 130,
      "cg": "",
      "animated_cg": null,
      "dialogue": [
        {
          "next_frame": 22,
          "character_id": 1025,
          "speaker_name": "マンハッタンカフェ",
          "text": "一体、誰を追いかけているんですか……？",
          "flag_type": "",
          "flag": "",
          "choices": []
        }
      ]
    },
    "22": {
      "frame_id": 22,
      "background_id": 74,
      "sub_background_id": 130,
      "cg": "",
      "animated_cg": null,
      "dialogue": [
        {
          "next_frame": 23,
          "character_id": 1025,
          "speaker_name": "マンハッタンカフェ",
          "text": "……アナタの前には……誰も見えない……。\r アナタにも、アナタにだけ見える…… 『お友だち』が……？",
          "flag_type": "",
          "flag": "",
          "choices": []
        }
      ]
    },
    "23": {
      "frame_id": 23,
      "background_id": 74,
      "sub_background_id": 130,
      "cg": "",
      "animated_cg": null,
      "dialogue": [
        {
          "next_frame": 24,
          "character_id": 0,
          "speaker_name": "明るい髪色のウマ娘",
          "text": "え……ええっと……。\r 『お友だち』というか……その。",
          "flag_type": "",
          "flag": "",
          "choices": []
        }
      ]
    },
    "24": {
      "frame_id": 24,
      "background_id": 74,
      "sub_background_id": 130,
      "cg": "",
      "animated_cg": null,
      "dialogue": [
        {
          "next_frame": 25,
          "character_id": 0,
          "speaker_name": "明るい髪色のウマ娘",
          "text": "カ……カフェさんがいます！",
          "flag_type": "",
          "flag": "",
          "choices": []
        }
      ]
    },
    "25": {
      "frame_id": 25,
      "background_id": 74,
      "sub_background_id": 130,
      "cg": "",
      "animated_cg": null,
      "dialogue": [
        {
          "next_frame": 26,
          "character_id": 1025,
          "speaker_name": "マンハッタンカフェ",
          "text": "私……？",
          "flag_type": "",
          "flag": "",
          "choices": []
        }
      ]
    },
    "26": {
      "frame_id": 26,
      "background_id": 74,
      "sub_background_id": 130,
      "cg": "",
      "animated_cg": null,
      "dialogue": [
        {
          "next_frame": 27,
          "character_id": 0,
          "speaker_name": "明るい髪色のウマ娘",
          "text": "はい！\r 私、カフェさんにとても憧れているので！",
          "flag_type": "",
          "flag": "",
          "choices": []
        }
      ]
    },
    "27": {
      "frame_id": 27,
      "background_id": 74,
      "sub_background_id": 130,
      "cg": "",
      "animated_cg": null,
      "dialogue": [
        {
          "next_frame": 28,
          "character_id": 1025,
          "speaker_name": "マンハッタンカフェ",
          "text": "――――",
          "flag_type": "",
          "flag": "",
          "choices": []
        }
      ]
    },
    "28": {
      "frame_id": 28,
      "background_id": 74,
      "sub_background_id": 130,
      "cg": "",
      "animated_cg": null,
      "dialogue": [
        {
          "next_frame": 29,
          "character_id": 0,
          "speaker_name": "明るい髪色のウマ娘",
          "text": "カフェさんの走りって、なんていうか\r すごく強い意志が感じられて……。",
          "flag_type": "",
          "flag": "",
          "choices": []
        }
      ]
    },
    "29": {
      "frame_id": 29,
      "background_id": 74,
      "sub_background_id": 130,
      "cg": "",
      "animated_cg": null,
      "dialogue": [
        {
          "next_frame": 30,
          "character_id": 0,
          "speaker_name": "明るい髪色のウマ娘",
          "text": "追われる『お友だち』が羨ましくて、\r 追い続けるカフェさんの背中を…… 私も追いかけたいって思ったんです。",
          "flag_type": "",
          "flag": "",
          "choices": []
        }
      ]
    },
    "30": {
      "frame_id": 30,
      "background_id": 74,
      "sub_background_id": 130,
      "cg": "",
      "animated_cg": null,
      "dialogue": [
        {
          "next_frame": 31,
          "character_id": 1025,
          "speaker_name": "マンハッタンカフェ",
          "text": "……私の……背中を……。",
          "flag_type": "",
          "flag": "",
          "choices": []
        }
      ]
    },
    "31": {
      "frame_id": 31,
      "background_id": 74,
      "sub_background_id": 130,
      "cg": "",
      "animated_cg": null,
      "dialogue": [
        {
          "next_frame": 32,
          "character_id": 0,
          "speaker_name": "明るい髪色のウマ娘",
          "text": "はい！　何度でも挑戦するあなたの背中に、\r 私もいつか……必ず追いつけるように…… 絶対、諦めません！",
          "flag_type": "",
          "flag": "",
          "choices": []
        }
      ]
    },
    "32": {
      "frame_id": 32,
      "background_id": 74,
      "sub_background_id": 130,
      "cg": "",
      "animated_cg": null,
      "dialogue": [
        {
          "next_frame": 33,
          "character_id": 1025,
          "speaker_name": "マンハッタンカフェ",
          "text": "…………。",
          "flag_type": "",
          "flag": "",
          "choices": []
        }
      ]
    },
    "33": {
      "frame_id": 33,
      "background_id": 74,
      "sub_background_id": 130,
      "cg": "",
      "animated_cg": null,
      "dialogue": [
        {
          "next_frame": 34,
          "character_id": 1025,
          "speaker_name": "マンハッタンカフェ",
          "text": "……私の背中を追う……ウマ娘がいるとは……\r 思いませんでした……。",
          "flag_type": "",
          "flag": "",
          "choices": []
        }
      ]
    },
    "34": {
      "frame_id": 34,
      "background_id": 74,
      "sub_background_id": 130,
      "cg": "",
      "animated_cg": null,
      "dialogue": [
        {
          "next_frame": 35,
          "character_id": 1025,
          "speaker_name": "マンハッタンカフェ",
          "text": "私は……前しか見ていなかったから……\r ずっと『お友だち』しか…… 見ていなかったから……。",
          "flag_type": "",
          "flag": "",
          "choices": []
        }
      ]
    },
    "35": {
      "frame_id": 35,
      "background_id": 74,
      "sub_background_id": 130,
      "cg": "",
      "animated_cg": null,
      "dialogue": [
        {
          "next_frame": 36,
          "character_id": 1025,
          "speaker_name": "マンハッタンカフェ",
          "text": "……とても不思議な気持ちです……。\r 彼女にとって、私は……。",
          "flag_type": "",
          "flag": "",
          "choices": [
            {
              "next_frame": 36,
              "loop_ends_at_frame": -1,
              "text": "『お友だち』なのかな",
              "flag_type": "",
              "flag": ""
            }
          ]
        }
      ]
    },
    "36": {
      "frame_id": 36,
      "background_id": 74,
      "sub_background_id": 130,
      "cg": "",
      "animated_cg": null,
      "dialogue": [
        {
          "next_frame": 37,
          "character_id": 1025,
          "speaker_name": "マンハッタンカフェ",
          "text": "……どうでしょう。\r それは……わかりませんが……でも……。",
          "flag_type": "",
          "flag": "",
          "choices": []
        }
      ]
    },
    "37": {
      "frame_id": 37,
      "background_id": 37,
      "sub_background_id": 130,
      "cg": "",
      "animated_cg": null,
      "dialogue": [
        {
          "next_frame": 38,
          "character_id": 1025,
          "speaker_name": "マンハッタンカフェ",
          "text": "追いつきたい私……誰かに追いつきたいと……\r 思ってもらえる私……。",
          "flag_type": "",
          "flag": "",
          "choices": []
        }
      ]
    },
    "38": {
      "frame_id": 38,
      "background_id": 37,
      "sub_background_id": 130,
      "cg": "",
      "animated_cg": null,
      "dialogue": [
        {
          "next_frame": 39,
          "character_id": 1025,
          "speaker_name": "マンハッタンカフェ",
          "text": "……それに相応しい走りが……\r できたらいいと……思いました……。",
          "flag_type": "",
          "flag": "",
          "choices": [
            {
              "next_frame": 39,
              "loop_ends_at_frame": -1,
              "text": "そうだな",
              "flag_type": "",
              "flag": "male_trainer"
            },
            {
              "next_frame": 39,
              "loop_ends_at_frame": -1,
              "text": "そうだね",
              "flag_type": "",
              "flag": "female_trainer"
            }
          ]
        }
      ]
    },
    "39": {
      "frame_id": 39,
      "background_id": 37,
      "sub_background_id": 130,
      "cg": "",
      "animated_cg": null,
      "dialogue": [
        {
          "next_frame": 40,
          "character_id": 1025,
          "speaker_name": "マンハッタンカフェ",
          "text": "……それと……。",
          "flag_type": "",
          "flag": "",
          "choices": []
        }
      ]
    },
    "40": {
      "frame_id": 40,
      "background_id": 74,
      "sub_background_id": 130,
      "cg": "",
      "animated_cg": null,
      "dialogue": [
        {
          "next_frame": 41,
          "character_id": 1025,
          "speaker_name": "マンハッタンカフェ",
          "text": "明日……病院へ……\r お見舞いに……行ってみます……。",
          "flag_type": "",
          "flag": "",
          "choices": [
            {
              "next_frame": 41,
              "loop_ends_at_frame": -1,
              "text": "え？病院？",
              "flag_type": "",
              "flag": ""
            }
          ]
        }
      ]
    },
    "41": {
      "frame_id": 41,
      "background_id": 74,
      "sub_background_id": 130,
      "cg": "",
      "animated_cg": null,
      "dialogue": [
        {
          "next_frame": 42,
          "character_id": 1025,
          "speaker_name": "マンハッタンカフェ",
          "text": "せっかくなら……生身の彼女とも、\r 走ってみたいので……。",
          "flag_type": "",
          "flag": "",
          "choices": []
        }
      ]
    },
    "42": {
      "frame_id": 42,
      "background_id": 74,
      "sub_background_id": 130,
      "cg": "",
      "animated_cg": null,
      "dialogue": [
        {
          "next_frame": -1,
          "character_id": 90001,
          "speaker_name": "モノローグ",
          "text": "マンハッタンカフェは小さくお辞儀をして、\r いつの間にか誰もいなくなったコースへと、 走りに行ったのだった。",
          "flag_type": "",
          "flag": "",
          "choices": []
        }
      ]
    }
  }
}