{
  "story_id": "501074116",
  "casts": [
    0,
    1027,
    1059,
    1064,
    1071,
    90001,
    1074,
    90770,
    1013,
    -1
  ],
  "frames": {
    "0": {
      "frame_id": 0,
      "background_id": 3,
      "sub_background_id": 110,
      "cg": "",
      "animated_cg": null,
      "dialogue": [
        {
          "next_frame": 1,
          "character_id": -1,
          "speaker_name": "",
          "text": "",
          "flag_type": "",
          "flag": "",
          "choices": []
        }
      ]
    },
    "1": {
      "frame_id": 1,
      "background_id": 3,
      "sub_background_id": 110,
      "cg": "",
      "animated_cg": null,
      "dialogue": [
        {
          "next_frame": 2,
          "character_id": 90001,
          "speaker_name": "モノローグ",
          "text": "――ある日。校門前に、メジロブライトが\r 笑顔で立っていた。",
          "flag_type": "",
          "flag": "",
          "choices": []
        }
      ]
    },
    "2": {
      "frame_id": 2,
      "background_id": 3,
      "sub_background_id": 110,
      "cg": "",
      "animated_cg": null,
      "dialogue": [
        {
          "next_frame": 3,
          "character_id": 1074,
          "speaker_name": "メジロブライト",
          "text": "トレーナーさま。今日はトレセン学園の\r 授業やトレーニングは、特別に お休みですのよ。",
          "flag_type": "",
          "flag": "",
          "choices": []
        }
      ]
    },
    "3": {
      "frame_id": 3,
      "background_id": 3,
      "sub_background_id": 110,
      "cg": "",
      "animated_cg": null,
      "dialogue": [
        {
          "next_frame": 4,
          "character_id": 1074,
          "speaker_name": "メジロブライト",
          "text": "さあどうぞ。\r どうぞお乗りくださいませ。",
          "flag_type": "",
          "flag": "",
          "choices": []
        }
      ]
    },
    "4": {
      "frame_id": 4,
      "background_id": 3,
      "sub_background_id": 110,
      "cg": "",
      "animated_cg": null,
      "dialogue": [
        {
          "next_frame": 5,
          "character_id": 90001,
          "speaker_name": "モノローグ",
          "text": "校門に横づけされた黒い大型セダンの扉が\r 開かれる。うやうやしく頭を下げる 黒服の運転手……。",
          "flag_type": "",
          "flag": "",
          "choices": [
            {
              "next_frame": 5,
              "loop_ends_at_frame": -1,
              "text": "どこへ行くんだ？",
              "flag_type": "",
              "flag": "male_trainer"
            },
            {
              "next_frame": 5,
              "loop_ends_at_frame": -1,
              "text": "どこへ行くの？",
              "flag_type": "",
              "flag": "female_trainer"
            }
          ]
        }
      ]
    },
    "5": {
      "frame_id": 5,
      "background_id": 3,
      "sub_background_id": 110,
      "cg": "",
      "animated_cg": null,
      "dialogue": [
        {
          "next_frame": 6,
          "character_id": 1074,
          "speaker_name": "メジロブライト",
          "text": "うふふ～、決まっていますわ～。\r トレーナーさまにとっての第二の家。",
          "flag_type": "",
          "flag": "",
          "choices": []
        }
      ]
    },
    "6": {
      "frame_id": 6,
      "background_id": 37,
      "sub_background_id": 110,
      "cg": "",
      "animated_cg": null,
      "dialogue": [
        {
          "next_frame": 7,
          "character_id": 1074,
          "speaker_name": "メジロブライト",
          "text": "――メジロのお屋敷ですわ。",
          "flag_type": "",
          "flag": "",
          "choices": []
        }
      ]
    },
    "7": {
      "frame_id": 7,
      "background_id": 154,
      "sub_background_id": 110,
      "cg": "",
      "animated_cg": null,
      "dialogue": [
        {
          "next_frame": 8,
          "character_id": 90001,
          "speaker_name": "モノローグ",
          "text": "――生きた心地がしなかった。中央には\r メジロのおばあ様。そして――",
          "flag_type": "",
          "flag": "",
          "choices": []
        }
      ]
    },
    "8": {
      "frame_id": 8,
      "background_id": 154,
      "sub_background_id": 110,
      "cg": "",
      "animated_cg": null,
      "dialogue": [
        {
          "next_frame": 9,
          "character_id": 90001,
          "speaker_name": "モノローグ",
          "text": "メジロ家を代表するウマ娘たちが勢ぞろい。\r 何か重要な話し合いが行われることだけは、 空気でわかる。",
          "flag_type": "",
          "flag": "",
          "choices": []
        }
      ]
    },
    "9": {
      "frame_id": 9,
      "background_id": 154,
      "sub_background_id": 110,
      "cg": "",
      "animated_cg": null,
      "dialogue": [
        {
          "next_frame": 10,
          "character_id": 1071,
          "speaker_name": "メジロアルダン",
          "text": "それでは僭越ながら、私、メジロアルダンが\r 本日の進行を務めさせていただきます。",
          "flag_type": "",
          "flag": "",
          "choices": []
        }
      ]
    },
    "10": {
      "frame_id": 10,
      "background_id": 154,
      "sub_background_id": 110,
      "cg": "",
      "animated_cg": null,
      "dialogue": [
        {
          "next_frame": 11,
          "character_id": 1071,
          "speaker_name": "メジロアルダン",
          "text": "議題はここ数年、ウマ娘界をにぎわせている\r “新しい流れ”について。",
          "flag_type": "",
          "flag": "",
          "choices": []
        }
      ]
    },
    "11": {
      "frame_id": 11,
      "background_id": 154,
      "sub_background_id": 110,
      "cg": "",
      "animated_cg": null,
      "dialogue": [
        {
          "next_frame": 12,
          "character_id": 1071,
          "speaker_name": "メジロアルダン",
          "text": "つまり加速する“スピード重視の流れ”に\r ついてです。",
          "flag_type": "",
          "flag": "",
          "choices": []
        }
      ]
    },
    "12": {
      "frame_id": 12,
      "background_id": 154,
      "sub_background_id": 110,
      "cg": "",
      "animated_cg": null,
      "dialogue": [
        {
          "next_frame": 13,
          "character_id": 1071,
          "speaker_name": "メジロアルダン",
          "text": "――スライドをお願いします。",
          "flag_type": "",
          "flag": "",
          "choices": []
        }
      ]
    },
    "13": {
      "frame_id": 13,
      "background_id": 154,
      "sub_background_id": 110,
      "cg": "",
      "animated_cg": null,
      "dialogue": [
        {
          "next_frame": 14,
          "character_id": 0,
          "speaker_name": "メジロ家の執事",
          "text": "……はい。では。",
          "flag_type": "",
          "flag": "",
          "choices": []
        }
      ]
    },
    "14": {
      "frame_id": 14,
      "background_id": 154,
      "sub_background_id": 110,
      "cg": "",
      "animated_cg": null,
      "dialogue": [
        {
          "next_frame": 15,
          "character_id": 90001,
          "speaker_name": "モノローグ",
          "text": "“スピード重視の流れ”。\r 気になる文言とともに映像が再生された。",
          "flag_type": "",
          "flag": "",
          "choices": []
        }
      ]
    },
    "15": {
      "frame_id": 15,
      "background_id": 72,
      "sub_background_id": 110,
      "cg": "",
      "animated_cg": null,
      "dialogue": [
        {
          "next_frame": 16,
          "character_id": 1071,
          "speaker_name": "メジロアルダン",
          "text": "少し前まで、ウマ娘界ではスピードも\r スタミナも同様に重んじられてきました。",
          "flag_type": "",
          "flag": "",
          "choices": []
        }
      ]
    },
    "16": {
      "frame_id": 16,
      "background_id": 72,
      "sub_background_id": 110,
      "cg": "",
      "animated_cg": null,
      "dialogue": [
        {
          "next_frame": 17,
          "character_id": 1071,
          "speaker_name": "メジロアルダン",
          "text": "しかし昨今は、スピード重視に大きく流れが\r 傾きつつあります。",
          "flag_type": "",
          "flag": "",
          "choices": []
        }
      ]
    },
    "17": {
      "frame_id": 17,
      "background_id": 15,
      "sub_background_id": 110,
      "cg": "",
      "animated_cg": null,
      "dialogue": [
        {
          "next_frame": 18,
          "character_id": 1071,
          "speaker_name": "メジロアルダン",
          "text": "レースタイムも速くなり、\r トレーニング内容もスピード強化が主流。 それに合わせて……。",
          "flag_type": "",
          "flag": "",
          "choices": []
        }
      ]
    },
    "18": {
      "frame_id": 18,
      "background_id": 15,
      "sub_background_id": 110,
      "cg": "",
      "animated_cg": null,
      "dialogue": [
        {
          "next_frame": 19,
          "character_id": 1071,
          "speaker_name": "メジロアルダン",
          "text": "『菊花賞』や『天皇賞（春）』のような\r 権威ある長距離レースを、無理して狙わない 陣営も増えてきています。",
          "flag_type": "",
          "flag": "",
          "choices": []
        }
      ]
    },
    "19": {
      "frame_id": 19,
      "background_id": 95,
      "sub_background_id": 110,
      "cg": "",
      "animated_cg": null,
      "dialogue": [
        {
          "next_frame": 20,
          "character_id": 1071,
          "speaker_name": "メジロアルダン",
          "text": "――これまでにない新スピード時代。\r その中でも、とくに目を引くウマ娘を 挙げるとするならば――",
          "flag_type": "",
          "flag": "",
          "choices": []
        }
      ]
    },
    "20": {
      "frame_id": 20,
      "background_id": 55,
      "sub_background_id": 110,
      "cg": "",
      "animated_cg": null,
      "dialogue": [
        {
          "next_frame": 21,
          "character_id": 1071,
          "speaker_name": "メジロアルダン",
          "text": "マーベラスサンデーさん。\r そしてスペシャルウィークさんらが 挙げられるでしょう。",
          "flag_type": "",
          "flag": "",
          "choices": []
        }
      ]
    },
    "21": {
      "frame_id": 21,
      "background_id": 55,
      "sub_background_id": 110,
      "cg": "",
      "animated_cg": null,
      "dialogue": [
        {
          "next_frame": 22,
          "character_id": 1071,
          "speaker_name": "メジロアルダン",
          "text": "彼女たちは、これまでの常識では\r 考えられない未知の加速を見せる時がある。 さらに――",
          "flag_type": "",
          "flag": "",
          "choices": []
        }
      ]
    },
    "22": {
      "frame_id": 22,
      "background_id": 55,
      "sub_background_id": 110,
      "cg": "",
      "animated_cg": null,
      "dialogue": [
        {
          "next_frame": 23,
          "character_id": 1071,
          "speaker_name": "メジロアルダン",
          "text": "同様の特徴はここ数年、クラシックGⅠを\r 勝った何人かのウマ娘にも見られるようです。",
          "flag_type": "",
          "flag": "",
          "choices": []
        }
      ]
    },
    "23": {
      "frame_id": 23,
      "background_id": 154,
      "sub_background_id": 110,
      "cg": "",
      "animated_cg": null,
      "dialogue": [
        {
          "next_frame": 24,
          "character_id": 1071,
          "speaker_name": "メジロアルダン",
          "text": "彼女たちの持つスピードは、これまでに\r なかったものと言えるでしょう。 さて――",
          "flag_type": "",
          "flag": "",
          "choices": []
        }
      ]
    },
    "24": {
      "frame_id": 24,
      "background_id": 154,
      "sub_background_id": 110,
      "cg": "",
      "animated_cg": null,
      "dialogue": [
        {
          "next_frame": 25,
          "character_id": 1071,
          "speaker_name": "メジロアルダン",
          "text": "本来ならば、今の時期は『天皇賞（春）』を\r 誰が制するかで持ちきりでした。しかし――",
          "flag_type": "",
          "flag": "",
          "choices": []
        }
      ]
    },
    "25": {
      "frame_id": 25,
      "background_id": 154,
      "sub_background_id": 110,
      "cg": "",
      "animated_cg": null,
      "dialogue": [
        {
          "next_frame": 26,
          "character_id": 1071,
          "speaker_name": "メジロアルダン",
          "text": "その風潮も若干変わり、時代の関心は\r 中距離に傾きつつあります。",
          "flag_type": "",
          "flag": "",
          "choices": []
        }
      ]
    },
    "26": {
      "frame_id": 26,
      "background_id": 154,
      "sub_background_id": 110,
      "cg": "",
      "animated_cg": null,
      "dialogue": [
        {
          "next_frame": 27,
          "character_id": 1071,
          "speaker_name": "メジロアルダン",
          "text": "この流れをどう考え、どう向き合って\r いくのかが、本日の議題です。",
          "flag_type": "",
          "flag": "",
          "choices": []
        }
      ]
    },
    "27": {
      "frame_id": 27,
      "background_id": 154,
      "sub_background_id": 110,
      "cg": "",
      "animated_cg": null,
      "dialogue": [
        {
          "next_frame": 28,
          "character_id": 1074,
          "speaker_name": "メジロブライト",
          "text": "まあ、トレーナーさま……すごいことに\r なってきましたわね～。",
          "flag_type": "",
          "flag": "",
          "choices": [
            {
              "next_frame": 28,
              "loop_ends_at_frame": -1,
              "text": "ああ……",
              "flag_type": "",
              "flag": "male_trainer"
            },
            {
              "next_frame": 28,
              "loop_ends_at_frame": -1,
              "text": "うん……",
              "flag_type": "",
              "flag": "female_trainer"
            }
          ]
        }
      ]
    },
    "28": {
      "frame_id": 28,
      "background_id": 154,
      "sub_background_id": 110,
      "cg": "",
      "animated_cg": null,
      "dialogue": [
        {
          "next_frame": 29,
          "character_id": 90001,
          "speaker_name": "モノローグ",
          "text": "スピード重視の新時代と、それに対する\r メジロ家の在り方。まさにそれは 名家の大会議だった。",
          "flag_type": "",
          "flag": "",
          "choices": []
        }
      ]
    },
    "29": {
      "frame_id": 29,
      "background_id": 154,
      "sub_background_id": 110,
      "cg": "",
      "animated_cg": null,
      "dialogue": [
        {
          "next_frame": 30,
          "character_id": 90770,
          "speaker_name": "メジロ家のおばあ様",
          "text": "総合力からスピードへ。その波は昔から\r だんだん高まってきてはいたのですが……。",
          "flag_type": "",
          "flag": "",
          "choices": []
        }
      ]
    },
    "30": {
      "frame_id": 30,
      "background_id": 154,
      "sub_background_id": 110,
      "cg": "",
      "animated_cg": null,
      "dialogue": [
        {
          "next_frame": 31,
          "character_id": 90770,
          "speaker_name": "メジロ家のおばあ様",
          "text": "より顕著になったのは、あのウマ娘の\r 登場あたりからかもしれません。",
          "flag_type": "",
          "flag": "",
          "choices": []
        }
      ]
    },
    "31": {
      "frame_id": 31,
      "background_id": 154,
      "sub_background_id": 110,
      "cg": "",
      "animated_cg": null,
      "dialogue": [
        {
          "next_frame": 32,
          "character_id": 90770,
          "speaker_name": "メジロ家のおばあ様",
          "text": "執事。あの映像を。",
          "flag_type": "",
          "flag": "",
          "choices": []
        }
      ]
    },
    "32": {
      "frame_id": 32,
      "background_id": 154,
      "sub_background_id": 110,
      "cg": "",
      "animated_cg": null,
      "dialogue": [
        {
          "next_frame": 33,
          "character_id": 0,
          "speaker_name": "メジロ家の執事",
          "text": "――は。",
          "flag_type": "",
          "flag": "",
          "choices": []
        }
      ]
    },
    "33": {
      "frame_id": 33,
      "background_id": 56,
      "sub_background_id": 111,
      "cg": "",
      "animated_cg": null,
      "dialogue": [
        {
          "next_frame": 34,
          "character_id": 90770,
          "speaker_name": "メジロ家のおばあ様",
          "text": "――フジキセキ。まるで奇術かと\r 思えるようなスピードで、 ジュニア級王者に輝いたウマ娘。",
          "flag_type": "",
          "flag": "",
          "choices": []
        }
      ]
    },
    "34": {
      "frame_id": 34,
      "background_id": 56,
      "sub_background_id": 111,
      "cg": "",
      "animated_cg": null,
      "dialogue": [
        {
          "next_frame": 35,
          "character_id": 90770,
          "speaker_name": "メジロ家のおばあ様",
          "text": "『あんな走りがありうるのか』と、\r 多くの関係者が衝撃を受け、 変化はより加速しました……。",
          "flag_type": "",
          "flag": "",
          "choices": []
        }
      ]
    },
    "35": {
      "frame_id": 35,
      "background_id": 154,
      "sub_background_id": 110,
      "cg": "",
      "animated_cg": null,
      "dialogue": [
        {
          "next_frame": 36,
          "character_id": 90770,
          "speaker_name": "メジロ家のおばあ様",
          "text": "時代の大勢を変えることはできないでしょう。\r しかし、その流れの中でメジロが どうあるべきかは、また別です。",
          "flag_type": "",
          "flag": "",
          "choices": []
        }
      ]
    },
    "36": {
      "frame_id": 36,
      "background_id": 154,
      "sub_background_id": 110,
      "cg": "",
      "animated_cg": null,
      "dialogue": [
        {
          "next_frame": 37,
          "character_id": 90770,
          "speaker_name": "メジロ家のおばあ様",
          "text": "メジロ家の方針は『天皇賞（春）』に\r 代表される長距離レースにも勝ててこそ、 強いウマ娘――というもの。",
          "flag_type": "",
          "flag": "",
          "choices": []
        }
      ]
    },
    "37": {
      "frame_id": 37,
      "background_id": 154,
      "sub_background_id": 110,
      "cg": "",
      "animated_cg": null,
      "dialogue": [
        {
          "next_frame": 38,
          "character_id": 90770,
          "speaker_name": "メジロ家のおばあ様",
          "text": "しかし1人1人の研鑽の時間も限られる中、\r 全て旧態依然のままでいいのか。",
          "flag_type": "",
          "flag": "",
          "choices": []
        }
      ]
    },
    "38": {
      "frame_id": 38,
      "background_id": 154,
      "sub_background_id": 110,
      "cg": "",
      "animated_cg": null,
      "dialogue": [
        {
          "next_frame": 39,
          "character_id": 90770,
          "speaker_name": "メジロ家のおばあ様",
          "text": "おそらく議論の余地はあるでしょう。\r ですから今日は皆で思う存分、語らいなさい。",
          "flag_type": "",
          "flag": "",
          "choices": []
        }
      ]
    },
    "39": {
      "frame_id": 39,
      "background_id": 154,
      "sub_background_id": 110,
      "cg": "",
      "animated_cg": null,
      "dialogue": [
        {
          "next_frame": 40,
          "character_id": 90770,
          "speaker_name": "メジロ家のおばあ様",
          "text": "そして、それぞれがメジロは\r どうありたいのか、考えるといいでしょう。",
          "flag_type": "",
          "flag": "",
          "choices": []
        }
      ]
    },
    "40": {
      "frame_id": 40,
      "background_id": 154,
      "sub_background_id": 110,
      "cg": "",
      "animated_cg": null,
      "dialogue": [
        {
          "next_frame": 41,
          "character_id": 90001,
          "speaker_name": "モノローグ",
          "text": "――そう言い残すと、おばあ様は出ていった。",
          "flag_type": "",
          "flag": "",
          "choices": []
        }
      ]
    },
    "41": {
      "frame_id": 41,
      "background_id": 154,
      "sub_background_id": 110,
      "cg": "",
      "animated_cg": null,
      "dialogue": [
        {
          "next_frame": 42,
          "character_id": 1027,
          "speaker_name": "メジロライアン",
          "text": "うーん、おばあ様の言う通り、\r 考えなきゃなとは思うんだけど……。",
          "flag_type": "",
          "flag": "",
          "choices": []
        }
      ]
    },
    "42": {
      "frame_id": 42,
      "background_id": 154,
      "sub_background_id": 110,
      "cg": "",
      "animated_cg": null,
      "dialogue": [
        {
          "next_frame": 43,
          "character_id": 1027,
          "speaker_name": "メジロライアン",
          "text": "そんなには意識しなくてもいいような？\r 目標ややるべきトレーニングは それぞれなんだし。",
          "flag_type": "",
          "flag": "",
          "choices": []
        }
      ]
    },
    "43": {
      "frame_id": 43,
      "background_id": 154,
      "sub_background_id": 110,
      "cg": "",
      "animated_cg": null,
      "dialogue": [
        {
          "next_frame": 44,
          "character_id": 1064,
          "speaker_name": "メジロパーマー",
          "text": "でもでも、みんながちょっ速で、\r びゅーんって行かれたら、 追いつけなくなるかもよ？",
          "flag_type": "",
          "flag": "",
          "choices": []
        }
      ]
    },
    "44": {
      "frame_id": 44,
      "background_id": 154,
      "sub_background_id": 110,
      "cg": "",
      "animated_cg": null,
      "dialogue": [
        {
          "next_frame": 45,
          "character_id": 1071,
          "speaker_name": "メジロアルダン",
          "text": "そうですね……。しかしだからといって\r メジロの家風を変えるのはよくないと 思います。",
          "flag_type": "",
          "flag": "",
          "choices": []
        }
      ]
    },
    "45": {
      "frame_id": 45,
      "background_id": 154,
      "sub_background_id": 110,
      "cg": "",
      "animated_cg": null,
      "dialogue": [
        {
          "next_frame": 46,
          "character_id": 1071,
          "speaker_name": "メジロアルダン",
          "text": "安易に迎合すれば、文化を失うだけ。\r そういう考えもありますから。",
          "flag_type": "",
          "flag": "",
          "choices": []
        }
      ]
    },
    "46": {
      "frame_id": 46,
      "background_id": 154,
      "sub_background_id": 110,
      "cg": "",
      "animated_cg": null,
      "dialogue": [
        {
          "next_frame": 47,
          "character_id": 1059,
          "speaker_name": "メジロドーベル",
          "text": "だったらやっぱり、ライアンの言う通り、\r 放っておけばいいんじゃない？",
          "flag_type": "",
          "flag": "",
          "choices": []
        }
      ]
    },
    "47": {
      "frame_id": 47,
      "background_id": 154,
      "sub_background_id": 110,
      "cg": "",
      "animated_cg": null,
      "dialogue": [
        {
          "next_frame": 48,
          "character_id": 1059,
          "speaker_name": "メジロドーベル",
          "text": "『今っぽい走りじゃない』って、\r ファンに少しぐらいそっぽ向かれても、 気にしなければ……。",
          "flag_type": "",
          "flag": "",
          "choices": []
        }
      ]
    },
    "48": {
      "frame_id": 48,
      "background_id": 154,
      "sub_background_id": 110,
      "cg": "",
      "animated_cg": null,
      "dialogue": [
        {
          "next_frame": 49,
          "character_id": 1013,
          "speaker_name": "メジロマックイーン",
          "text": "でもそれは――勝てれば、の話ですわ。",
          "flag_type": "",
          "flag": "",
          "choices": []
        }
      ]
    },
    "49": {
      "frame_id": 49,
      "background_id": 154,
      "sub_background_id": 110,
      "cg": "",
      "animated_cg": null,
      "dialogue": [
        {
          "next_frame": 50,
          "character_id": 1027,
          "speaker_name": "メジロライアン",
          "text": "え、マックイーン……。",
          "flag_type": "",
          "flag": "",
          "choices": []
        }
      ]
    },
    "50": {
      "frame_id": 50,
      "background_id": 154,
      "sub_background_id": 110,
      "cg": "",
      "animated_cg": null,
      "dialogue": [
        {
          "next_frame": 51,
          "character_id": 1013,
          "speaker_name": "メジロマックイーン",
          "text": "たとえ静視しようが、レースの文化は刻々と\r 変わり続けます。レース体系すら 変わることもありえますわ。",
          "flag_type": "",
          "flag": "",
          "choices": []
        }
      ]
    },
    "51": {
      "frame_id": 51,
      "background_id": 154,
      "sub_background_id": 110,
      "cg": "",
      "animated_cg": null,
      "dialogue": [
        {
          "next_frame": 52,
          "character_id": 1013,
          "speaker_name": "メジロマックイーン",
          "text": "メジロが長距離で全勝しても、それ以外の\r 中距離レースで後れを取り、さらに レース数のバランスまで変われば……。",
          "flag_type": "",
          "flag": "",
          "choices": []
        }
      ]
    },
    "52": {
      "frame_id": 52,
      "background_id": 154,
      "sub_background_id": 110,
      "cg": "",
      "animated_cg": null,
      "dialogue": [
        {
          "next_frame": 53,
          "character_id": 1013,
          "speaker_name": "メジロマックイーン",
          "text": "きっと威光は薄れるでしょう。そして\r 言われる。『メジロ家は勢いを失った』と。",
          "flag_type": "",
          "flag": "",
          "choices": []
        }
      ]
    },
    "53": {
      "frame_id": 53,
      "background_id": 154,
      "sub_background_id": 110,
      "cg": "",
      "animated_cg": null,
      "dialogue": [
        {
          "next_frame": 54,
          "character_id": 1013,
          "speaker_name": "メジロマックイーン",
          "text": "その世評を跳ね返せなければ、\r あるいはそのまま時代の波に……。",
          "flag_type": "",
          "flag": "",
          "choices": []
        }
      ]
    },
    "54": {
      "frame_id": 54,
      "background_id": 154,
      "sub_background_id": 110,
      "cg": "",
      "animated_cg": null,
      "dialogue": [
        {
          "next_frame": 55,
          "character_id": 1064,
          "speaker_name": "メジロパーマー",
          "text": "じゃあ私たちも、この流れに乗っとく？\r もっともっとスピード磨く感じで。",
          "flag_type": "",
          "flag": "",
          "choices": []
        }
      ]
    },
    "55": {
      "frame_id": 55,
      "background_id": 154,
      "sub_background_id": 110,
      "cg": "",
      "animated_cg": null,
      "dialogue": [
        {
          "next_frame": 56,
          "character_id": 1059,
          "speaker_name": "メジロドーベル",
          "text": "それはそれで、なんか納得いかないけど。\r アタシは結構スピードも大事にしてるけど あくまでメジロ流っていうか……。",
          "flag_type": "",
          "flag": "",
          "choices": []
        }
      ]
    },
    "56": {
      "frame_id": 56,
      "background_id": 154,
      "sub_background_id": 110,
      "cg": "",
      "animated_cg": null,
      "dialogue": [
        {
          "next_frame": 57,
          "character_id": 90001,
          "speaker_name": "モノローグ",
          "text": "さまざまな意見が飛び交う。どれもが\r 正論だけに、なかなかひとつにまとまらない。",
          "flag_type": "",
          "flag": "",
          "choices": []
        }
      ]
    },
    "57": {
      "frame_id": 57,
      "background_id": 154,
      "sub_background_id": 110,
      "cg": "",
      "animated_cg": null,
      "dialogue": [
        {
          "next_frame": 58,
          "character_id": 90001,
          "speaker_name": "モノローグ",
          "text": "そんな中、メジロマックイーンの目が――",
          "flag_type": "",
          "flag": "",
          "choices": []
        }
      ]
    },
    "58": {
      "frame_id": 58,
      "background_id": 154,
      "sub_background_id": 110,
      "cg": "",
      "animated_cg": null,
      "dialogue": [
        {
          "next_frame": 59,
          "character_id": 1013,
          "speaker_name": "メジロマックイーン",
          "text": "――トレーナーさん、\r 貴方はどう思いますの？",
          "flag_type": "",
          "flag": "",
          "choices": []
        }
      ]
    },
    "59": {
      "frame_id": 59,
      "background_id": 154,
      "sub_background_id": 110,
      "cg": "",
      "animated_cg": null,
      "dialogue": [
        {
          "next_frame": 60,
          "character_id": 1013,
          "speaker_name": "メジロマックイーン",
          "text": "参考までに聞きたいですわ。\r この場でただ1人、メジロの外から メジロを見ているものとして。",
          "flag_type": "",
          "flag": "",
          "choices": []
        }
      ]
    },
    "60": {
      "frame_id": 60,
      "background_id": 154,
      "sub_background_id": 110,
      "cg": "",
      "animated_cg": null,
      "dialogue": [
        {
          "next_frame": 61,
          "character_id": 90001,
          "speaker_name": "モノローグ",
          "text": "いきなり発言を求められた。喉にグッと\r 詰まるものを感じるが、応じないわけにも いかない。",
          "flag_type": "",
          "flag": "",
          "choices": []
        }
      ]
    },
    "61": {
      "frame_id": 61,
      "background_id": 154,
      "sub_background_id": 110,
      "cg": "",
      "animated_cg": null,
      "dialogue": [
        {
          "next_frame": 62,
          "character_id": 1074,
          "speaker_name": "メジロブライト",
          "text": "トレーナーさま……。",
          "flag_type": "",
          "flag": "",
          "choices": []
        }
      ]
    },
    "62": {
      "frame_id": 62,
      "background_id": 154,
      "sub_background_id": 110,
      "cg": "",
      "animated_cg": null,
      "dialogue": [
        {
          "next_frame": 63,
          "character_id": 90001,
          "speaker_name": "モノローグ",
          "text": "メジロブライトが優しく微笑む。\r それに勇気づけられた。",
          "flag_type": "",
          "flag": "",
          "choices": []
        }
      ]
    },
    "63": {
      "frame_id": 63,
      "background_id": 154,
      "sub_background_id": 110,
      "cg": "",
      "animated_cg": null,
      "dialogue": [
        {
          "next_frame": 64,
          "character_id": 90001,
          "speaker_name": "モノローグ",
          "text": "メジロブライトこそ、メジロの伝統を\r 継ぐもの。象徴である彼女の来た道と 行く道が正しいとするならば――",
          "flag_type": "",
          "flag": "",
          "choices": [
            {
              "next_frame": 64,
              "loop_ends_at_frame": -1,
              "text": "今のまま……全部で勝てばいいと思う",
              "flag_type": "",
              "flag": ""
            }
          ]
        }
      ]
    },
    "64": {
      "frame_id": 64,
      "background_id": 154,
      "sub_background_id": 110,
      "cg": "",
      "animated_cg": null,
      "dialogue": [
        {
          "next_frame": 65,
          "character_id": 1013,
          "speaker_name": "メジロマックイーン",
          "text": "今のままで、全部？　スタミナを有したまま、\r スピード勝負も同じようにですか？",
          "flag_type": "",
          "flag": "",
          "choices": [
            {
              "next_frame": 65,
              "loop_ends_at_frame": -1,
              "text": "それがメジロだと思ってるけど",
              "flag_type": "",
              "flag": ""
            }
          ]
        }
      ]
    },
    "65": {
      "frame_id": 65,
      "background_id": 154,
      "sub_background_id": 110,
      "cg": "",
      "animated_cg": null,
      "dialogue": [
        {
          "next_frame": 66,
          "character_id": 90001,
          "speaker_name": "モノローグ",
          "text": "実際そうだった。メジロ家のウマ娘は\r 中距離、長距離あらゆるレースを制してきた。",
          "flag_type": "",
          "flag": "",
          "choices": []
        }
      ]
    },
    "66": {
      "frame_id": 66,
      "background_id": 154,
      "sub_background_id": 110,
      "cg": "",
      "animated_cg": null,
      "dialogue": [
        {
          "next_frame": 67,
          "character_id": 90001,
          "speaker_name": "モノローグ",
          "text": "今まで通りのやり方を磨くのが、\r 1番いいように思える。メジロブライトが そうしているように。",
          "flag_type": "",
          "flag": "",
          "choices": []
        }
      ]
    },
    "67": {
      "frame_id": 67,
      "background_id": 154,
      "sub_background_id": 110,
      "cg": "",
      "animated_cg": null,
      "dialogue": [
        {
          "next_frame": 68,
          "character_id": 1064,
          "speaker_name": "メジロパーマー",
          "text": "なるほど～。\r さすがブライトのトレーナーさん。",
          "flag_type": "",
          "flag": "",
          "choices": []
        }
      ]
    },
    "68": {
      "frame_id": 68,
      "background_id": 154,
      "sub_background_id": 110,
      "cg": "",
      "animated_cg": null,
      "dialogue": [
        {
          "next_frame": 69,
          "character_id": 1064,
          "speaker_name": "メジロパーマー",
          "text": "度胸、据わってるね！\r 地震が来ても、笑ってそう。",
          "flag_type": "",
          "flag": "",
          "choices": []
        }
      ]
    },
    "69": {
      "frame_id": 69,
      "background_id": 154,
      "sub_background_id": 110,
      "cg": "",
      "animated_cg": null,
      "dialogue": [
        {
          "next_frame": 70,
          "character_id": 1013,
          "speaker_name": "メジロマックイーン",
          "text": "『言うは易く、行うは難し』ですわ。\r トレーナーさん、わかっていますの？",
          "flag_type": "",
          "flag": "",
          "choices": []
        }
      ]
    },
    "70": {
      "frame_id": 70,
      "background_id": 154,
      "sub_background_id": 110,
      "cg": "",
      "animated_cg": null,
      "dialogue": [
        {
          "next_frame": 71,
          "character_id": 1013,
          "speaker_name": "メジロマックイーン",
          "text": "それを1人のウマ娘が為しうるには\r 『天皇賞（春）』を勝ち、さらには……。",
          "flag_type": "",
          "flag": "",
          "choices": []
        }
      ]
    },
    "71": {
      "frame_id": 71,
      "background_id": 154,
      "sub_background_id": 110,
      "cg": "",
      "animated_cg": null,
      "dialogue": [
        {
          "next_frame": 72,
          "character_id": 1013,
          "speaker_name": "メジロマックイーン",
          "text": "その脚で、速度至上の時代に\r 立ち向かわなくてはなりませんのよ？",
          "flag_type": "",
          "flag": "",
          "choices": []
        }
      ]
    },
    "72": {
      "frame_id": 72,
      "background_id": 154,
      "sub_background_id": 110,
      "cg": "",
      "animated_cg": null,
      "dialogue": [
        {
          "next_frame": 73,
          "character_id": 90001,
          "speaker_name": "モノローグ",
          "text": "言われて、少し怖気づく。\r 確かに大変そうだが……。",
          "flag_type": "",
          "flag": "",
          "choices": []
        }
      ]
    },
    "73": {
      "frame_id": 73,
      "background_id": 154,
      "sub_background_id": 110,
      "cg": "",
      "animated_cg": null,
      "dialogue": [
        {
          "next_frame": 74,
          "character_id": 1074,
          "speaker_name": "メジロブライト",
          "text": "でもマックイーンさま。わたくしと\r トレーナーさまは、それをやりますのよ。",
          "flag_type": "",
          "flag": "",
          "choices": []
        }
      ]
    },
    "74": {
      "frame_id": 74,
      "background_id": 154,
      "sub_background_id": 110,
      "cg": "",
      "animated_cg": null,
      "dialogue": [
        {
          "next_frame": 75,
          "character_id": 1074,
          "speaker_name": "メジロブライト",
          "text": "やらせていただきたいんですの。\r ですから、まずは――",
          "flag_type": "",
          "flag": "",
          "choices": []
        }
      ]
    },
    "75": {
      "frame_id": 75,
      "background_id": 95,
      "sub_background_id": 110,
      "cg": "",
      "animated_cg": null,
      "dialogue": [
        {
          "next_frame": 76,
          "character_id": 1074,
          "speaker_name": "メジロブライト",
          "text": "『天皇賞（春）』を必ず勝ちますわ。\r そして……。",
          "flag_type": "",
          "flag": "",
          "choices": []
        }
      ]
    },
    "76": {
      "frame_id": 76,
      "background_id": 95,
      "sub_background_id": 110,
      "cg": "",
      "animated_cg": null,
      "dialogue": [
        {
          "next_frame": 77,
          "character_id": 1074,
          "speaker_name": "メジロブライト",
          "text": "その盾を手に、時代と向き合いたいのです。\r メジロを護り抜くために。",
          "flag_type": "",
          "flag": "",
          "choices": []
        }
      ]
    },
    "77": {
      "frame_id": 77,
      "background_id": 154,
      "sub_background_id": 110,
      "cg": "",
      "animated_cg": null,
      "dialogue": [
        {
          "next_frame": 78,
          "character_id": 1027,
          "speaker_name": "メジロライアン",
          "text": "ブライト、君は……。",
          "flag_type": "",
          "flag": "",
          "choices": []
        }
      ]
    },
    "78": {
      "frame_id": 78,
      "background_id": 154,
      "sub_background_id": 110,
      "cg": "",
      "animated_cg": null,
      "dialogue": [
        {
          "next_frame": 79,
          "character_id": 1074,
          "speaker_name": "メジロブライト",
          "text": "大好きなメジロが揺らいでしまうのは、\r とても悲しいことですのよ。ですから～。",
          "flag_type": "",
          "flag": "",
          "choices": []
        }
      ]
    },
    "79": {
      "frame_id": 79,
      "background_id": 154,
      "sub_background_id": 110,
      "cg": "",
      "animated_cg": null,
      "dialogue": [
        {
          "next_frame": 80,
          "character_id": 1074,
          "speaker_name": "メジロブライト",
          "text": "わたくしとトレーナーさまが、\r しっかりと護り切ってみせますわ。",
          "flag_type": "",
          "flag": "",
          "choices": [
            {
              "next_frame": 80,
              "loop_ends_at_frame": -1,
              "text": "ブライト……",
              "flag_type": "",
              "flag": ""
            }
          ]
        }
      ]
    },
    "80": {
      "frame_id": 80,
      "background_id": 154,
      "sub_background_id": 110,
      "cg": "",
      "animated_cg": null,
      "dialogue": [
        {
          "next_frame": 81,
          "character_id": 1074,
          "speaker_name": "メジロブライト",
          "text": "トレーナーさま、手を貸して\r くださいますわよね？ 大丈夫、わたくしたちならば……。",
          "flag_type": "",
          "flag": "",
          "choices": []
        }
      ]
    },
    "81": {
      "frame_id": 81,
      "background_id": 154,
      "sub_background_id": 110,
      "cg": "",
      "animated_cg": null,
      "dialogue": [
        {
          "next_frame": 82,
          "character_id": 1074,
          "speaker_name": "メジロブライト",
          "text": "そのために出会ったのですから。\r 長い長い歴史の中で。",
          "flag_type": "",
          "flag": "",
          "choices": []
        }
      ]
    },
    "82": {
      "frame_id": 82,
      "background_id": 154,
      "sub_background_id": 110,
      "cg": "",
      "animated_cg": null,
      "dialogue": [
        {
          "next_frame": 83,
          "character_id": 1013,
          "speaker_name": "メジロマックイーン",
          "text": "……いいでしょう。おばあ様には、\r そう伝えておきますわ。メジロは今のまま スピードでも上回ると。",
          "flag_type": "",
          "flag": "",
          "choices": []
        }
      ]
    },
    "83": {
      "frame_id": 83,
      "background_id": 154,
      "sub_background_id": 110,
      "cg": "",
      "animated_cg": null,
      "dialogue": [
        {
          "next_frame": 84,
          "character_id": 1013,
          "speaker_name": "メジロマックイーン",
          "text": "ふふっ、たまには珍しいお客様を招くのも\r いいですわね。会議がはかどりますわ。",
          "flag_type": "",
          "flag": "",
          "choices": []
        }
      ]
    },
    "84": {
      "frame_id": 84,
      "background_id": 37,
      "sub_background_id": 120,
      "cg": "",
      "animated_cg": null,
      "dialogue": [
        {
          "next_frame": 85,
          "character_id": 90001,
          "speaker_name": "モノローグ",
          "text": "こうして……いきなり飛び出した\r メジロブライト『天皇賞（春）』必勝の誓い。",
          "flag_type": "",
          "flag": "",
          "choices": []
        }
      ]
    },
    "85": {
      "frame_id": 85,
      "background_id": 37,
      "sub_background_id": 120,
      "cg": "",
      "animated_cg": null,
      "dialogue": [
        {
          "next_frame": -1,
          "character_id": 90001,
          "speaker_name": "モノローグ",
          "text": "後に退くわけにはいかない。その先に待つ\r 新時代のスピードを誇るウマ娘たちに 勝つためにも。",
          "flag_type": "",
          "flag": "",
          "choices": []
        }
      ]
    }
  }
}